{
  "project_info": {
    "project_number": "1014306765807",
    "project_id": "urticaria-16d4d",
    "storage_bucket": "urticaria-16d4d.firebasestorage.app"
  },
  "client": [
    {
      "client_info": {
        "mobilesdk_app_id": "1:1014306765807:android:9a0d5e32c3436bc386d41a",
        "android_client_info": {
          "package_name": "com.example.urticaria"
        }
      },
      "oauth_client": [],
      "api_key": [
        {
          "current_key": "AIzaSyAbXevJH8sCvYOrxtOi_GYKIDazOE0xf90"
        }
      ],
      "services": {
        "appinvite_service": {
          "other_platform_oauth_client": []
        }
      }
    }
  ],
  "configuration_version": "1"
}